tauphahji_cmd/__init__.py
Tau_Phah_Ji_Command-1.0.0.dist-info/LICENSE
Tau_Phah_Ji_Command-1.0.0.dist-info/METADATA
Tau_Phah_Ji_Command-1.0.0.dist-info/WHEEL
Tau_Phah_Ji_Command-1.0.0.dist-info/top_level.txt
Tau_Phah_Ji_Command-1.0.0.dist-info/RECORD
