Metadata-Version: 2.1
Name: Tau-Phah-Ji-Command
Version: 1.0.0
Summary: 用指令叫鬥拍字
Author-email: A-hông <hong@ithuan.tw>
License: MIT License        
Project-URL: Homepage, https://github.com/i3thuan5/Tau-Phah-Ji-Command
Keywords: 台語,Taiwan,Natural Language,Corpus
Classifier: Programming Language :: Python :: 3
Classifier: License :: OSI Approved :: MIT License
Classifier: Operating System :: OS Independent
Classifier: Topic :: Scientific/Engineering
Classifier: Topic :: Scientific/Engineering :: Information Analysis
Classifier: Topic :: Text Processing
Classifier: Topic :: Text Processing :: Linguistic
Classifier: License :: OSI Approved :: MIT License
License-File: LICENSE
Requires-Dist: tai5-uan5-gian5-gi2-kang1-ku7
